[{"id_verbos":12056,"nome":"zabumbar"},{"id_verbos":12057,"nome":"zagaiar"},{"id_verbos":12058,"nome":"zagunchar"},{"id_verbos":12059,"nome":"zampar"},{"id_verbos":12060,"nome":"zangar"},{"id_verbos":12061,"nome":"zangarrear"},{"id_verbos":12064,"nome":"zaranzar"},{"id_verbos":12065,"nome":"zarelhar"},{"id_verbos":12066,"nome":"zargunchar"},{"id_verbos":12067,"nome":"zarpar"},{"id_verbos":12068,"nome":"zavar"},{"id_verbos":12069,"nome":"zebrar"},{"id_verbos":12070,"nome":"zelar"},{"id_verbos":12072,"nome":"ziguezaguear"},{"id_verbos":12073,"nome":"zimbrar"},{"id_verbos":12074,"nome":"zincar"},{"id_verbos":12075,"nome":"zincografar"},{"id_verbos":12076,"nome":"zincogravar"},{"id_verbos":12077,"nome":"zingar"},{"id_verbos":12078,"nome":"zingarear"},{"id_verbos":12079,"nome":"zingrar"},{"id_verbos":12080,"nome":"zinir"},{"id_verbos":12082,"nome":"ziziar"},{"id_verbos":12083,"nome":"zoar"},{"id_verbos":12084,"nome":"zombar"},{"id_verbos":12085,"nome":"zombetear"},{"id_verbos":12088,"nome":"zonzear"},{"id_verbos":12089,"nome":"zoografar"},{"id_verbos":12091,"nome":"zuir"},{"id_verbos":12092,"nome":"zumbaiar"},{"id_verbos":12093,"nome":"zumbar"},{"id_verbos":12094,"nome":"zumbir"},{"id_verbos":12096,"nome":"zunir"},{"id_verbos":12097,"nome":"zunzunar"},{"id_verbos":12099,"nome":"zupar"},{"id_verbos":12100,"nome":"zurrar"},{"id_verbos":12102,"nome":"zurzir"}]