[{"id_verbos":1776,"nome":"habitar"},{"id_verbos":1777,"nome":"habituar"},{"id_verbos":1778,"nome":"harmonizar"},{"id_verbos":1779,"nome":"haver"},{"id_verbos":1780,"nome":"hebetar"},{"id_verbos":1781,"nome":"helenizar"},{"id_verbos":1782,"nome":"herdar"},{"id_verbos":1783,"nome":"hesitar"},{"id_verbos":1784,"nome":"hibernar"},{"id_verbos":1785,"nome":"hilarizar"},{"id_verbos":1786,"nome":"hiperligar"},{"id_verbos":1787,"nome":"hipnotizar"},{"id_verbos":1788,"nome":"hispidar"},{"id_verbos":1789,"nome":"hominizar"},{"id_verbos":1790,"nome":"homiziar"},{"id_verbos":1791,"nome":"homologar"},{"id_verbos":1792,"nome":"hospitalar"},{"id_verbos":1793,"nome":"hostilizar"},{"id_verbos":1794,"nome":"humectar"},{"id_verbos":1795,"nome":"humedecer"},{"id_verbos":1796,"nome":"humilhar"}]